src/crawler/main.py
useless_crawler-0.0.5.dist-info/METADATA
useless_crawler-0.0.5.dist-info/WHEEL
useless_crawler-0.0.5.dist-info/licenses/LICENSE
useless_crawler-0.0.5.dist-info/RECORD
