Metadata-Version: 2.1
Name: useless_crawler
Version: 0.0.5
Summary: A simple crawler that acts as the backbone for other operations
Project-URL: Homepage, https://github.com/bmelton/python-crawler
Project-URL: Bug Tracker, https://github.com/bmelton/python-crawler/issues
Author-email: Barry Melton <barry@sureisfun.com>
License-File: LICENSE
Classifier: License :: OSI Approved :: MIT License
Classifier: Operating System :: OS Independent
Classifier: Programming Language :: Python :: 3
Requires-Python: >=3.7
